README.md
setup.cfg
setup.py
nsrx.egg-info/PKG-INFO
nsrx.egg-info/SOURCES.txt
nsrx.egg-info/dependency_links.txt
nsrx.egg-info/entry_points.txt
nsrx.egg-info/requires.txt
nsrx.egg-info/top_level.txt
nsrx_class/__init__.py
nsrx_class/_configurations_.py
nsrx_class/_main_functions_.py
nsrx_class/all_address_type.py
nsrx_class/all_applications_type.py
nsrx_class/all_policy_type.py
nsrx_class/cli_loop.py
nsrx_class/devices.py
nsrx_class/excel_output.py
nsrx_class/load_full_set_configurations.py
nsrx_class/logger_config.py
nsrx_class/main_script.py
nsrx_class/match_policy.py
nsrx_class/save_excel_def.py